grayven/__init__.py
grayven/exceptions.py
grayven/grand_comics_database.py
grayven/sqlite_cache.py
grayven/schemas/__init__.py
grayven/schemas/issue.py
grayven/schemas/publisher.py
grayven/schemas/series.py
grayven-0.4.0.dist-info/METADATA
grayven-0.4.0.dist-info/WHEEL
grayven-0.4.0.dist-info/licenses/LICENSE
grayven-0.4.0.dist-info/RECORD
