Metadata-Version: 2.4
Name: Grayven
Version: 0.4.0
Summary: A Python wrapper for the Grand Comics Database API.
Project-URL: Homepage, https://pypi.org/project/Grayven
Project-URL: Issues, https://github.com/Metron-Project/Grayven/issues
Project-URL: Source, https://github.com/Metron-Project/Grayven
Author-email: BuriedInCode <BuriedInCode@tuta.io>
Maintainer-email: BuriedInCode <BuriedInCode@tuta.io>
License: MIT
License-File: LICENSE
Keywords: comic,comics,metadata
Classifier: Development Status :: 4 - Beta
Classifier: Environment :: Console
Classifier: Intended Audience :: Developers
Classifier: License :: OSI Approved :: MIT License
Classifier: Natural Language :: English
Classifier: Operating System :: MacOS
Classifier: Operating System :: Microsoft :: Windows
Classifier: Operating System :: POSIX :: Linux
Classifier: Programming Language :: Python
Classifier: Programming Language :: Python :: 3.10
Classifier: Programming Language :: Python :: 3.11
Classifier: Programming Language :: Python :: 3.12
Classifier: Programming Language :: Python :: 3.13
Classifier: Programming Language :: Python :: 3.14
Classifier: Topic :: Internet
Classifier: Typing :: Typed
Requires-Python: >=3.10
Requires-Dist: httpx>=0.28.0
Requires-Dist: pydantic>=2.12.0
Requires-Dist: pyrate-limiter>=3.9.0
